abcSphinx/__init__.py
abcSphinx/abc.css
abcSphinx/abc2svg.py
abcsphinx-1.3.15.dist-info/LICENSE
abcsphinx-1.3.15.dist-info/METADATA
abcsphinx-1.3.15.dist-info/WHEEL
abcsphinx-1.3.15.dist-info/top_level.txt
abcsphinx-1.3.15.dist-info/RECORD
