Metadata-Version: 2.2
Name: abcsphinx
Version: 1.3.15
Summary: sphinx 用于渲染ABC代码的扩展库.
Classifier: Programming Language :: Python :: 3
Classifier: License :: OSI Approved :: Apache Software License
Requires-Python: >=3.10
License-File: LICENSE
Requires-Dist: sphinx
Requires-Dist: myst-parser
